mkdocs_autolinktitle/__init__.py
mkdocs_autolinktitle/plugin.py
mkdocs_autolinktitle-0.1.0.dist-info/METADATA
mkdocs_autolinktitle-0.1.0.dist-info/WHEEL
mkdocs_autolinktitle-0.1.0.dist-info/entry_points.txt
mkdocs_autolinktitle-0.1.0.dist-info/RECORD
