Metadata-Version: 2.3
Name: mkdocs-autolinktitle
Version: 0.1.0
Summary: Add your description here
Author-email: yamionp <yami@crimsondream.jp>
Requires-Python: >=3.8
